zarrify/__about__.py
zarrify/__init__.py
zarrify/to_zarr.py
zarrify/formats/__init__.py
zarrify/formats/mrc.py
zarrify/formats/n5.py
zarrify/formats/tiff.py
zarrify/formats/tiff_stack.py
zarrify/utils/__init__.py
zarrify/utils/dask_utils.py
zarrify/utils/volume.py
zarrify-0.0.8.dist-info/licenses/LICENSE.txt
zarrify-0.0.8.dist-info/METADATA
zarrify-0.0.8.dist-info/WHEEL
zarrify-0.0.8.dist-info/entry_points.txt
zarrify-0.0.8.dist-info/top_level.txt
zarrify-0.0.8.dist-info/RECORD
